[
    {
        "0xD3A5654A109D32Ca852B309fbD4D9EE449dF172b": [
            {
                "pool": "0x2d073839e9d7d3b1028f35da54a40ff1562cee60",
                "feeFactor": "0.9985947383062085",
                "balAndRatioFactor": "0.96",
                "wrapFactor": "1",
                "valueUSD": "0",
                "factorUSD": "0"
            },
            {
                "pool": "0xbf41971ef92df39016fb705a7ef56bb5eb203fee",
                "feeFactor": "0.9985947383062085",
                "balAndRatioFactor": "1",
                "wrapFactor": "1",
                "valueUSD": "0",
                "factorUSD": "0"
            },
            {
                "pool": "0xe9a5dd29c6949b3f5c0ba0162223c5b4830a8416",
                "feeFactor": "0.9985947383062085",
                "balAndRatioFactor": "0.96",
                "wrapFactor": "1",
                "valueUSD": "0",
                "factorUSD": "0"
            }
        ],
        "0x726DcCC7a2842cc2a4ADDf5349E9a206fEf9b69a": [
            {
                "pool": "0x5fa00d2ba520f95f548ff0813f9f74facdf1b807",
                "feeFactor": "0.9985947383062085",
                "balAndRatioFactor": "1",
                "wrapFactor": "1",
                "valueUSD": "4949.080401294988554257",
                "factorUSD": "4942.125648187554442111"
            }
        ],
        "0x1c5302aD98765D84f980a8B382EF51814A0ed2d9": [
            {
                "pool": "0x8e31ae2ecf51943ff390d8119b407c22d554a1b0",
                "feeFactor": "0.9961013694701175",
                "balAndRatioFactor": "1",
                "wrapFactor": "1",
                "valueUSD": "6934.563615570053400396",
                "factorUSD": "6907.528314146979611172"
            },
            {
                "pool": "0xe3d6e11d567e2c3b4f81beb0c9fc42cc84b398a3",
                "feeFactor": "0.9961013694701175",
                "balAndRatioFactor": "1",
                "wrapFactor": "1",
                "valueUSD": "6517.102763714180394559",
                "factorUSD": "6491.694987913182667761"
            },
            {
                "pool": "0xf47c9eef21362e8423b1da3fd58209e36ca69467",
                "feeFactor": "0.9961013694701175",
                "balAndRatioFactor": "1",
                "wrapFactor": "1",
                "valueUSD": "980.096068449012946893",
                "factorUSD": "976.275035994339816557"
            }
        ],
        "0x88827b479eae4Ef7b01b7F6311C7dA3f37b8F635": [
            {
                "pool": "0x8e31ae2ecf51943ff390d8119b407c22d554a1b0",
                "feeFactor": "0.9961013694701175",
                "balAndRatioFactor": "1",
                "wrapFactor": "1",
                "valueUSD": "8.737505808579579514",
                "factorUSD": "8.703441501679225478"
            },
            {
                "pool": "0xe3d6e11d567e2c3b4f81beb0c9fc42cc84b398a3",
                "feeFactor": "0.9961013694701175",
                "balAndRatioFactor": "1",
                "wrapFactor": "1",
                "valueUSD": "36.894284459083559145",
                "factorUSD": "36.750447275313206487"
            }
        ],
        "0x2e3ceDAaAdB6cf955F6d4F5F7752A27278205768": [
            {
                "pool": "0x9fea8724b5243d8ae56b01891d57c1f5bf6f004f",
                "feeFactor": "0.9943907906910809",
                "balAndRatioFactor": "0.5078125",
                "wrapFactor": "1",
                "valueUSD": "0",
                "factorUSD": "0"
            }
        ],
        "0x00A5af2D7DA07dF76073A6f478f0fB4942D2659a": [
            {
                "pool": "0xe3d6e11d567e2c3b4f81beb0c9fc42cc84b398a3",
                "feeFactor": "0.9961013694701175",
                "balAndRatioFactor": "1",
                "wrapFactor": "1",
                "valueUSD": "8751.52832251455546327",
                "factorUSD": "8717.409347013268826831"
            }
        ],
        "0x4CA563F982e2e875B3D7774D58f5130f659e11d0": [
            {
                "pool": "0xe3d6e11d567e2c3b4f81beb0c9fc42cc84b398a3",
                "feeFactor": "0.9961013694701175",
                "balAndRatioFactor": "1",
                "wrapFactor": "1",
                "valueUSD": "0.675853606112072378",
                "factorUSD": "0.67321870260955267"
            }
        ],
        "0xa5a3DFAcA553B23aD5E3789b70cf7af30d2d64A6": [
            {
                "pool": "0xe3d6e11d567e2c3b4f81beb0c9fc42cc84b398a3",
                "feeFactor": "0.9961013694701175",
                "balAndRatioFactor": "1",
                "wrapFactor": "1",
                "valueUSD": "7.098183868192686512",
                "factorUSD": "7.070510671857431038"
            }
        ],
        "0xbE09EbCB9c02342c3C94c7a3DF8C9ce586e6F629": [
            {
                "pool": "0xe3d6e11d567e2c3b4f81beb0c9fc42cc84b398a3",
                "feeFactor": "0.9961013694701175",
                "balAndRatioFactor": "1",
                "wrapFactor": "1",
                "valueUSD": "77.901049378281849367",
                "factorUSD": "77.597341968865795526"
            }
        ],
        "0xC6cdDDC68202dccF0C66837DB0d1C7Df289cE92e": [
            {
                "pool": "0xe3d6e11d567e2c3b4f81beb0c9fc42cc84b398a3",
                "feeFactor": "0.9961013694701175",
                "balAndRatioFactor": "1",
                "wrapFactor": "1",
                "valueUSD": "283.860176380724150429",
                "factorUSD": "282.753510430868427641"
            }
        ],
        "0xd37CADbffd63C0D4DB739671c3f8ff52dfA70B9a": [
            {
                "pool": "0xe3d6e11d567e2c3b4f81beb0c9fc42cc84b398a3",
                "feeFactor": "0.9961013694701175",
                "balAndRatioFactor": "1",
                "wrapFactor": "1",
                "valueUSD": "5.351236356560805338",
                "factorUSD": "5.330373863128500182"
            }
        ],
        "0xf5433ADa2b03Db0380D8566Be17BC739d8a6e1Cc": [
            {
                "pool": "0xe3d6e11d567e2c3b4f81beb0c9fc42cc84b398a3",
                "feeFactor": "0.9961013694701175",
                "balAndRatioFactor": "1",
                "wrapFactor": "1",
                "valueUSD": "4.83490012485718079",
                "factorUSD": "4.816050635621479869"
            }
        ],
        "0x6c01fa4380C0274DA8D4f1476b2B59D2a62672f9": [
            {
                "pool": "0xf47c9eef21362e8423b1da3fd58209e36ca69467",
                "feeFactor": "0.9961013694701175",
                "balAndRatioFactor": "1",
                "wrapFactor": "1",
                "valueUSD": "13.4205566853868604",
                "factorUSD": "13.368234893365192496"
            }
        ],
        "0x909Fd983ab19BDB39d36B7d245D4E94a6E41b70A": [
            {
                "pool": "0xf47c9eef21362e8423b1da3fd58209e36ca69467",
                "feeFactor": "0.9961013694701175",
                "balAndRatioFactor": "1",
                "wrapFactor": "1",
                "valueUSD": "2.669967087217958359",
                "factorUSD": "2.659557872017948975"
            }
        ]
    },
    {
        "0xD3A5654A109D32Ca852B309fbD4D9EE449dF172b": "0",
        "0x726DcCC7a2842cc2a4ADDf5349E9a206fEf9b69a": "4.027644605558886755",
        "0x1c5302aD98765D84f980a8B382EF51814A0ed2d9": "11.715484885480326847",
        "0x88827b479eae4Ef7b01b7F6311C7dA3f37b8F635": "0.037043192133624911",
        "0x2e3ceDAaAdB6cf955F6d4F5F7752A27278205768": "0",
        "0x00A5af2D7DA07dF76073A6f478f0fB4942D2659a": "7.104357361659323782",
        "0x4CA563F982e2e875B3D7774D58f5130f659e11d0": "0.000548647660733001",
        "0xa5a3DFAcA553B23aD5E3789b70cf7af30d2d64A6": "0.005762197522537042",
        "0xbE09EbCB9c02342c3C94c7a3DF8C9ce586e6F629": "0.063238885053686877",
        "0xC6cdDDC68202dccF0C66837DB0d1C7Df289cE92e": "0.230433366542870791",
        "0xd37CADbffd63C0D4DB739671c3f8ff52dfA70B9a": "0.004344052147544012",
        "0xf5433ADa2b03Db0380D8566Be17BC739d8a6e1Cc": "0.003924898261089934",
        "0x6c01fa4380C0274DA8D4f1476b2B59D2a62672f9": "0.010894603453445627",
        "0x909Fd983ab19BDB39d36B7d245D4E94a6E41b70A": "0.002167438604142541"
    },
    {
        "0x471EcE3750Da237f93B8E339c536989b8978a438": "8009.593929087653065310390818625541740517",
        "0x765DE816845861e75A25fCA122bb6898B8B1282a": "7679.094753585349194141468070508428021706",
        "0xD8763CBa276a3738E6DE85b4b3bF5FDed6D6cA73": "7679.094753585349194141468070508428021706",
        "0xD629eb00dEced2a080B7EC630eF6aC117e614f1b": "2305.410585216219612216922748117113718811",
        "0x2DEf4285787d58a2f811AF24755A8150622f4361": "2305.410585216219612216922748117113718811",
        "0x00Be915B9dCf56a3CBE739D9B9c202ca692409EC": "496.1514143798614800075"
    }
]