[
    {
        "0xC4E1C8152EEb4b45b9D83C1fAa49df092dF08d51": [
            {
                "pool": "0x03d38716d7ebc6d40bcc7aa89e4757d4707c7a76",
                "feeFactor": "0.9985947383062085",
                "balAndRatioFactor": "0.64",
                "wrapFactor": "1",
                "valueUSD": "1.467481469514758021",
                "factorUSD": "0.937868335372352046"
            }
        ],
        "0xE2B52Fc1ad49B93F85C45315EcbAd740f17B0e8E": [
            {
                "pool": "0x06f40f1e128768cc6bdf4d009de103fa7deb73db",
                "feeFactor": "0.9961013694701175",
                "balAndRatioFactor": "0.96",
                "wrapFactor": "1",
                "valueUSD": "48.777900030955708157",
                "factorUSD": "46.644223699883008983"
            },
            {
                "pool": "0x79670b0cb738a0bd826bc7709bc363c6b554690b",
                "feeFactor": "0.9961013694701175",
                "balAndRatioFactor": "1",
                "wrapFactor": "1",
                "valueUSD": "1027.469371299084484354",
                "factorUSD": "1023.463647839618695473"
            },
            {
                "pool": "0xbf511ad7c4426980e27f6b84a2e3899c565b5c2b",
                "feeFactor": "0.9961013694701175",
                "balAndRatioFactor": "0.64",
                "wrapFactor": "1",
                "valueUSD": "6995.999087516054237056",
                "factorUSD": "4459.983534007317783062"
            }
        ],
        "0x048Ef78Ec97E1BcB8c1b4dc596AbAAAEAd117E28": [
            {
                "pool": "0x12a1b7db38fb29cbf07fbb071c41590364288c2a",
                "feeFactor": "0.9985947383062085",
                "balAndRatioFactor": "1",
                "wrapFactor": "0.1",
                "valueUSD": "0",
                "factorUSD": "0"
            },
            {
                "pool": "0x19143655196feb0a7d6455dc44d5519da357e76a",
                "feeFactor": "0.9985947383062085",
                "balAndRatioFactor": "0.19",
                "wrapFactor": "1",
                "valueUSD": "0",
                "factorUSD": "0"
            },
            {
                "pool": "0x226c3062380e306c99bb569eeebf69865c40b96c",
                "feeFactor": "0.9985947383062085",
                "balAndRatioFactor": "0.19",
                "wrapFactor": "1",
                "valueUSD": "0",
                "factorUSD": "0"
            },
            {
                "pool": "0x7a73bcf99b2ab9552949f3969b3f0529a446bdd9",
                "feeFactor": "0.9985947383062085",
                "balAndRatioFactor": "0.19",
                "wrapFactor": "1",
                "valueUSD": "0",
                "factorUSD": "0"
            },
            {
                "pool": "0x8a255897bd0766c6517de3b9d6a6cca0dc77a20d",
                "feeFactor": "0.9985947383062085",
                "balAndRatioFactor": "0.19",
                "wrapFactor": "1",
                "valueUSD": "0",
                "factorUSD": "0"
            },
            {
                "pool": "0x8c99d421985639615f730e603b807b62766ac4bf",
                "feeFactor": "0.9985947383062085",
                "balAndRatioFactor": "0.19",
                "wrapFactor": "1",
                "valueUSD": "0",
                "factorUSD": "0"
            },
            {
                "pool": "0x91aa762a6773c8e946193c46837421bc8d1095ae",
                "feeFactor": "0.9985947383062085",
                "balAndRatioFactor": "0.19",
                "wrapFactor": "1",
                "valueUSD": "0",
                "factorUSD": "0"
            },
            {
                "pool": "0x9b9240726171731942b66cde8463bdb2c67efd5c",
                "feeFactor": "0.9985947383062085",
                "balAndRatioFactor": "0.19",
                "wrapFactor": "1",
                "valueUSD": "0",
                "factorUSD": "0"
            },
            {
                "pool": "0xdabcd65a10ffa62264f7ec4af5086e0a8493b126",
                "feeFactor": "0.9985947383062085",
                "balAndRatioFactor": "0.19",
                "wrapFactor": "1",
                "valueUSD": "0",
                "factorUSD": "0"
            },
            {
                "pool": "0xec1ac89ae16826d762a59a5781fc2ad022fc2ca2",
                "feeFactor": "0.9985947383062085",
                "balAndRatioFactor": "1",
                "wrapFactor": "1",
                "valueUSD": "0",
                "factorUSD": "0"
            },
            {
                "pool": "0xf8fb53b06cfb75931cd2a0d1f79856061fd2309a",
                "feeFactor": "0.9985947383062085",
                "balAndRatioFactor": "1",
                "wrapFactor": "1",
                "valueUSD": "0",
                "factorUSD": "0"
            }
        ],
        "0xeaB998Fa7Db98bf17788cdEAD7C7755120a55281": [
            {
                "pool": "0x13885f41fc6aa20bd0f2480d6df1c41410b3948c",
                "feeFactor": "0.9739393463693841",
                "balAndRatioFactor": "1",
                "wrapFactor": "0.7",
                "valueUSD": "3.045246142445013132",
                "factorUSD": "2.076119526254749103"
            }
        ],
        "0x2B86486477D007b75286474458ED45594320a580": [
            {
                "pool": "0x1eb301fef9964864ee2d4b876024ca489ce7f50d",
                "feeFactor": "0.9985947383062085",
                "balAndRatioFactor": "0.19",
                "wrapFactor": "1",
                "valueUSD": "0.001244314582874656",
                "factorUSD": "0.0002360875390987"
            }
        ],
        "0x47cD5c37E276249C5DF6a94a4532E991A79788bD": [
            {
                "pool": "0x1eb301fef9964864ee2d4b876024ca489ce7f50d",
                "feeFactor": "0.9985947383062085",
                "balAndRatioFactor": "0.19",
                "wrapFactor": "1",
                "valueUSD": "0.111665364559129549",
                "factorUSD": "0.021186604644960354"
            },
            {
                "pool": "0xa59cf736fb8dec59a9171c62060e43208af0e07f",
                "feeFactor": "0.9985947383062085",
                "balAndRatioFactor": "0.19",
                "wrapFactor": "1",
                "valueUSD": "0.035337429098681606",
                "factorUSD": "0.006704676445010309"
            }
        ],
        "0x6A0491132aF4d0925F857A5000bb21e5C5C195EA": [
            {
                "pool": "0x1eb301fef9964864ee2d4b876024ca489ce7f50d",
                "feeFactor": "0.9985947383062085",
                "balAndRatioFactor": "0.19",
                "wrapFactor": "1",
                "valueUSD": "55919.466170960825659815",
                "factorUSD": "10609.768090570565905357"
            },
            {
                "pool": "0x79670b0cb738a0bd826bc7709bc363c6b554690b",
                "feeFactor": "0.9961013694701175",
                "balAndRatioFactor": "1",
                "wrapFactor": "1",
                "valueUSD": "66599.231031536592565157",
                "factorUSD": "66339.585236170346022216"
            },
            {
                "pool": "0xbf511ad7c4426980e27f6b84a2e3899c565b5c2b",
                "feeFactor": "0.9961013694701175",
                "balAndRatioFactor": "0.64",
                "wrapFactor": "1",
                "valueUSD": "110046.00070312881668218",
                "factorUSD": "70154.862083261521674254"
            }
        ],
        "0x752087ce92821c631ab223c487b9771a10C3595a": [
            {
                "pool": "0x1eb301fef9964864ee2d4b876024ca489ce7f50d",
                "feeFactor": "0.9985947383062085",
                "balAndRatioFactor": "0.19",
                "wrapFactor": "1",
                "valueUSD": "252.223216603276199652",
                "factorUSD": "47.855067625952760477"
            }
        ],
        "0xb8aC6ef01a6191C8689AD756B4a41dcaD7021390": [
            {
                "pool": "0x1eb301fef9964864ee2d4b876024ca489ce7f50d",
                "feeFactor": "0.9985947383062085",
                "balAndRatioFactor": "0.19",
                "wrapFactor": "1",
                "valueUSD": "0.036829859866514469",
                "factorUSD": "0.006987839812298706"
            },
            {
                "pool": "0x57614d2b55d05370e56e4b3847c1c4df337ed78a",
                "feeFactor": "0.9985947383062085",
                "balAndRatioFactor": "0.64",
                "wrapFactor": "1",
                "valueUSD": "124.391830252685584818",
                "factorUSD": "79.498897394310957518"
            }
        ],
        "0x2E748192b21Cbf86b80c15e75c3fdcBDf229bCdf": [
            {
                "pool": "0x1f9042df5c7d74ad14d7c66d1a4941b9b9a3d862",
                "feeFactor": "0.9394130628134758",
                "balAndRatioFactor": "0.979073591325945373",
                "wrapFactor": "0.969325153374233128",
                "valueUSD": "3.968189375207713135",
                "factorUSD": "2.936377558007954224"
            },
            {
                "pool": "0x35f1fcf808f1fdccf1ea0c30c48c7eddec970b27",
                "feeFactor": "0.9985947383062085",
                "balAndRatioFactor": "0.850090090090090088",
                "wrapFactor": "1",
                "valueUSD": "0.138011698964603138",
                "factorUSD": "0.117157508963231191"
            },
            {
                "pool": "0x3c820d8e4ee052fdad9f842a21be13c3eccb344e",
                "feeFactor": "0.9739393463693841",
                "balAndRatioFactor": "0.970296250026694",
                "wrapFactor": "0.962325581395348837",
                "valueUSD": "9.138195642432813689",
                "factorUSD": "7.47930521463310901"
            },
            {
                "pool": "0xa781f0ac89f43b3f3fc7d483a09937963e9d4505",
                "feeFactor": "0.9874235035173194",
                "balAndRatioFactor": "0.973792739639898318",
                "wrapFactor": "0.970172612197928653",
                "valueUSD": "5.317084137371848633",
                "factorUSD": "4.960124022986443182"
            }
        ],
        "0x59b8C949D5eB9feE0ba981fc3FDAa9E5B64652CE": [
            {
                "pool": "0x1f9042df5c7d74ad14d7c66d1a4941b9b9a3d862",
                "feeFactor": "0.9394130628134758",
                "balAndRatioFactor": "0.979073591325945373",
                "wrapFactor": "0.969325153374233128",
                "valueUSD": "2.435152780476128002",
                "factorUSD": "1.80196238102585044"
            },
            {
                "pool": "0x3bbdd935d015484f1f8aacd0573660ee39985b30",
                "feeFactor": "0.569782824730923",
                "balAndRatioFactor": "0.979073591325945373",
                "wrapFactor": "0.969325153374233128",
                "valueUSD": "1.779545917342744275",
                "factorUSD": "0.798695916135800351"
            },
            {
                "pool": "0xa781f0ac89f43b3f3fc7d483a09937963e9d4505",
                "feeFactor": "0.9874235035173194",
                "balAndRatioFactor": "0.973792739639898318",
                "wrapFactor": "0.970172612197928653",
                "valueUSD": "3.278442748315691954",
                "factorUSD": "3.058345930546842397"
            },
            {
                "pool": "0xcd65f38b298310fa2c8b1844ea187016f913b0c8",
                "feeFactor": "0.9961013694701175",
                "balAndRatioFactor": "0.96",
                "wrapFactor": "1",
                "valueUSD": "2.532210704301169429",
                "factorUSD": "2.421445008327634198"
            },
            {
                "pool": "0xde1595aaff23d277dbc4c53ca88e013cc4197d1a",
                "feeFactor": "0.569782824730923",
                "balAndRatioFactor": "0.979073591325945373",
                "wrapFactor": "0.969325153374233128",
                "valueUSD": "0.619473457119534421",
                "factorUSD": "0.278032117931916258"
            },
            {
                "pool": "0xe8ddbdc29f35708df8e7aeeee5f2a552596b6225",
                "feeFactor": "0.9766381514821663",
                "balAndRatioFactor": "0.974443507675150298",
                "wrapFactor": "1",
                "valueUSD": "2.567534912536334409",
                "factorUSD": "2.199121472993015812"
            },
            {
                "pool": "0xee66c663f05277895b178dfc501f3a9233573371",
                "feeFactor": "0.9874235035173194",
                "balAndRatioFactor": "0.978676830925079918",
                "wrapFactor": "1",
                "valueUSD": "0.573508399041619757",
                "factorUSD": "0.404580931641460371"
            },
            {
                "pool": "0xf04ee54189fc57d453df3e244485d1b2d6697420",
                "feeFactor": "0.9923729844257629",
                "balAndRatioFactor": "1",
                "wrapFactor": "0.7",
                "valueUSD": "0.105257678072934006",
                "factorUSD": "0.043871047971644755"
            }
        ],
        "0x5B878ba97Bae92fc0Aa6133edbF2f58D52350d65": [
            {
                "pool": "0x1f9042df5c7d74ad14d7c66d1a4941b9b9a3d862",
                "feeFactor": "0.9394130628134758",
                "balAndRatioFactor": "0.979073591325945373",
                "wrapFactor": "0.969325153374233128",
                "valueUSD": "1.073836293554302099",
                "factorUSD": "0.794616510257210692"
            },
            {
                "pool": "0x3bbdd935d015484f1f8aacd0573660ee39985b30",
                "feeFactor": "0.569782824730923",
                "balAndRatioFactor": "0.979073591325945373",
                "wrapFactor": "0.969325153374233128",
                "valueUSD": "2.481565499761773336",
                "factorUSD": "1.113776391475648741"
            },
            {
                "pool": "0xa781f0ac89f43b3f3fc7d483a09937963e9d4505",
                "feeFactor": "0.9874235035173194",
                "balAndRatioFactor": "0.973792739639898318",
                "wrapFactor": "0.970172612197928653",
                "valueUSD": "0.198982381917244176",
                "factorUSD": "0.185623786872523231"
            },
            {
                "pool": "0xde1595aaff23d277dbc4c53ca88e013cc4197d1a",
                "feeFactor": "0.569782824730923",
                "balAndRatioFactor": "0.979073591325945373",
                "wrapFactor": "0.969325153374233128",
                "valueUSD": "7.352132470972673203",
                "factorUSD": "3.299784581127109256"
            },
            {
                "pool": "0xe8ddbdc29f35708df8e7aeeee5f2a552596b6225",
                "feeFactor": "0.9766381514821663",
                "balAndRatioFactor": "0.974443507675150298",
                "wrapFactor": "1",
                "valueUSD": "3.20781890459506906",
                "factorUSD": "2.747531649958867225"
            },
            {
                "pool": "0xee66c663f05277895b178dfc501f3a9233573371",
                "feeFactor": "0.9874235035173194",
                "balAndRatioFactor": "0.978676830925079918",
                "wrapFactor": "1",
                "valueUSD": "6.091616319100172762",
                "factorUSD": "4.297324694289294676"
            },
            {
                "pool": "0xf04ee54189fc57d453df3e244485d1b2d6697420",
                "feeFactor": "0.9923729844257629",
                "balAndRatioFactor": "1",
                "wrapFactor": "0.7",
                "valueUSD": "0.305337154445094455",
                "factorUSD": "0.127263504149354362"
            },
            {
                "pool": "0xf38f097ba2904cbd0ae4c0ec4f091d401dbec1d7",
                "feeFactor": "0.9844964370054085",
                "balAndRatioFactor": "0.973792739639898318",
                "wrapFactor": "0.979286536248561565",
                "valueUSD": "2.807128188790588482",
                "factorUSD": "2.635437431108428468"
            }
        ],
        "0x719B8BE8E2c3f07575d41A2580011Db702029E5b": [
            {
                "pool": "0x1f9042df5c7d74ad14d7c66d1a4941b9b9a3d862",
                "feeFactor": "0.9394130628134758",
                "balAndRatioFactor": "0.979073591325945373",
                "wrapFactor": "0.969325153374233128",
                "valueUSD": "7.066514869543044496",
                "factorUSD": "5.229073946393890254"
            },
            {
                "pool": "0x3bbdd935d015484f1f8aacd0573660ee39985b30",
                "feeFactor": "0.569782824730923",
                "balAndRatioFactor": "0.979073591325945373",
                "wrapFactor": "0.969325153374233128",
                "valueUSD": "6.42661721556979631",
                "factorUSD": "2.884394763079898101"
            },
            {
                "pool": "0xa781f0ac89f43b3f3fc7d483a09937963e9d4505",
                "feeFactor": "0.9874235035173194",
                "balAndRatioFactor": "0.973792739639898318",
                "wrapFactor": "0.970172612197928653",
                "valueUSD": "0.343881945885602975",
                "factorUSD": "0.320795582087892769"
            },
            {
                "pool": "0xe8ddbdc29f35708df8e7aeeee5f2a552596b6225",
                "feeFactor": "0.9766381514821663",
                "balAndRatioFactor": "0.974443507675150298",
                "wrapFactor": "1",
                "valueUSD": "0.117289331624742637",
                "factorUSD": "0.100459583419713363"
            }
        ],
        "0x95577b29A69FBa8ed9373b9F194B6515A48A82dD": [
            {
                "pool": "0x1f9042df5c7d74ad14d7c66d1a4941b9b9a3d862",
                "feeFactor": "0.9394130628134758",
                "balAndRatioFactor": "0.979073591325945373",
                "wrapFactor": "0.969325153374233128",
                "valueUSD": "0.932421703874014512",
                "factorUSD": "0.689972656789314189"
            },
            {
                "pool": "0xb013b68d4da85e7368a6230eed32520666100a97",
                "feeFactor": "0.9985947383062085",
                "balAndRatioFactor": "1",
                "wrapFactor": "0.7",
                "valueUSD": "0.05036300776189067",
                "factorUSD": "0.015842053885234109"
            },
            {
                "pool": "0xcd65f38b298310fa2c8b1844ea187016f913b0c8",
                "feeFactor": "0.9961013694701175",
                "balAndRatioFactor": "0.96",
                "wrapFactor": "1",
                "valueUSD": "0.082987769038227834",
                "factorUSD": "0.079357661172718619"
            }
        ],
        "0x9b04A9EeE500302980A117F514bc2DE0Fd1f683d": [
            {
                "pool": "0x1f9042df5c7d74ad14d7c66d1a4941b9b9a3d862",
                "feeFactor": "0.9394130628134758",
                "balAndRatioFactor": "0.979073591325945373",
                "wrapFactor": "0.969325153374233128",
                "valueUSD": "28.260282286271047456",
                "factorUSD": "20.912020783794453476"
            },
            {
                "pool": "0x33e13746d3cb962388e656d5559f377cd6502b92",
                "feeFactor": "0.9961013694701175",
                "balAndRatioFactor": "1",
                "wrapFactor": "1",
                "valueUSD": "2.661184486796191038",
                "factorUSD": "2.650809511710317715"
            },
            {
                "pool": "0x3bbdd935d015484f1f8aacd0573660ee39985b30",
                "feeFactor": "0.569782824730923",
                "balAndRatioFactor": "0.979073591325945373",
                "wrapFactor": "0.969325153374233128",
                "valueUSD": "21.30982260467012189",
                "factorUSD": "9.564275988642719264"
            },
            {
                "pool": "0x3c820d8e4ee052fdad9f842a21be13c3eccb344e",
                "feeFactor": "0.9739393463693841",
                "balAndRatioFactor": "0.970296250026694",
                "wrapFactor": "0.962325581395348837",
                "valueUSD": "66.319352708552359587",
                "factorUSD": "54.280155509136654882"
            },
            {
                "pool": "0xde1595aaff23d277dbc4c53ca88e013cc4197d1a",
                "feeFactor": "0.569782824730923",
                "balAndRatioFactor": "0.979073591325945373",
                "wrapFactor": "0.969325153374233128",
                "valueUSD": "60.136810108330594715",
                "factorUSD": "26.99060708401315585"
            },
            {
                "pool": "0xf04ee54189fc57d453df3e244485d1b2d6697420",
                "feeFactor": "0.9923729844257629",
                "balAndRatioFactor": "1",
                "wrapFactor": "0.7",
                "valueUSD": "6.852313081899329695",
                "factorUSD": "2.856021160987736652"
            }
        ],
        "0xddf27151bcfe33DE396B472C5c5f8F48a64E3143": [
            {
                "pool": "0x27f38b24509b2b4262d9ff6c724dc34db6c31650",
                "feeFactor": "0.9985947383062085",
                "balAndRatioFactor": "0.330578512396694214",
                "wrapFactor": "1",
                "valueUSD": "0",
                "factorUSD": "0"
            }
        ],
        "0x9e31bBA0Fa35eE9E13106baE82BccA553e774ce9": [
            {
                "pool": "0x2d5244ec32dd21033d50d92c1c06bab199838251",
                "feeFactor": "0.9985947383062085",
                "balAndRatioFactor": "1",
                "wrapFactor": "0.1",
                "valueUSD": "0",
                "factorUSD": "0"
            }
        ],
        "0xdcb48866a5Cf353aCa79467EFf1E0fFB2EC9a1eE": [
            {
                "pool": "0x33e13746d3cb962388e656d5559f377cd6502b92",
                "feeFactor": "0.9961013694701175",
                "balAndRatioFactor": "1",
                "wrapFactor": "1",
                "valueUSD": "0.012739342172762901",
                "factorUSD": "0.012689676184437548"
            },
            {
                "pool": "0xb013b68d4da85e7368a6230eed32520666100a97",
                "feeFactor": "0.9985947383062085",
                "balAndRatioFactor": "1",
                "wrapFactor": "0.7",
                "valueUSD": "2.799412464993399771",
                "factorUSD": "0.880575745735734963"
            },
            {
                "pool": "0xf04ee54189fc57d453df3e244485d1b2d6697420",
                "feeFactor": "0.9923729844257629",
                "balAndRatioFactor": "1",
                "wrapFactor": "0.7",
                "valueUSD": "3.05337154445094463",
                "factorUSD": "1.272635041493543653"
            }
        ],
        "0x7A0Ea4409C480fF41bC8211768fB8947c20A91eC": [
            {
                "pool": "0x3bbdd935d015484f1f8aacd0573660ee39985b30",
                "feeFactor": "0.569782824730923",
                "balAndRatioFactor": "0.979073591325945373",
                "wrapFactor": "0.969325153374233128",
                "valueUSD": "2.32658934714073077",
                "factorUSD": "1.044219984422272804"
            },
            {
                "pool": "0x6e2b58dfce2b39495e28881b616e32df2dae8bdd",
                "feeFactor": "0.569782824730923",
                "balAndRatioFactor": "1",
                "wrapFactor": "1",
                "valueUSD": "1.233642744106177918",
                "factorUSD": "0.702908447445625264"
            },
            {
                "pool": "0xc25e1181cd0213cc321a7d34d641897240e484dd",
                "feeFactor": "0.9943907906910809",
                "balAndRatioFactor": "1",
                "wrapFactor": "0.1",
                "valueUSD": "4.05772141741536375",
                "factorUSD": "0.403496080866779708"
            },
            {
                "pool": "0xde1595aaff23d277dbc4c53ca88e013cc4197d1a",
                "feeFactor": "0.569782824730923",
                "balAndRatioFactor": "0.979073591325945373",
                "wrapFactor": "0.969325153374233128",
                "valueUSD": "12.632171360645686704",
                "factorUSD": "5.669571984262608417"
            },
            {
                "pool": "0xe8ddbdc29f35708df8e7aeeee5f2a552596b6225",
                "feeFactor": "0.9766381514821663",
                "balAndRatioFactor": "0.974443507675150298",
                "wrapFactor": "1",
                "valueUSD": "4.918412276510262194",
                "factorUSD": "4.212673408059496047"
            },
            {
                "pool": "0xf38f097ba2904cbd0ae4c0ec4f091d401dbec1d7",
                "feeFactor": "0.9844964370054085",
                "balAndRatioFactor": "0.973792739639898318",
                "wrapFactor": "0.979286536248561565",
                "valueUSD": "17.72250964530513639",
                "factorUSD": "16.638558039111202175"
            }
        ],
        "0xaefcD0F8a1cbD231CecAA9bfd9Ffb82a6eaaa462": [
            {
                "pool": "0x3c820d8e4ee052fdad9f842a21be13c3eccb344e",
                "feeFactor": "0.9739393463693841",
                "balAndRatioFactor": "0.970296250026694",
                "wrapFactor": "0.962325581395348837",
                "valueUSD": "23.739571385714193685",
                "factorUSD": "19.430039255655227469"
            },
            {
                "pool": "0x6e2b58dfce2b39495e28881b616e32df2dae8bdd",
                "feeFactor": "0.569782824730923",
                "balAndRatioFactor": "1",
                "wrapFactor": "1",
                "valueUSD": "0.060262858147297955",
                "factorUSD": "0.034336741541526345"
            },
            {
                "pool": "0xa781f0ac89f43b3f3fc7d483a09937963e9d4505",
                "feeFactor": "0.9874235035173194",
                "balAndRatioFactor": "0.973792739639898318",
                "wrapFactor": "0.970172612197928653",
                "valueUSD": "15.850045529518294594",
                "factorUSD": "14.785959666091030215"
            },
            {
                "pool": "0xad08a736ea1f26d4c2f86e18461e572ad7ab3c78",
                "feeFactor": "0.569782824730923",
                "balAndRatioFactor": "1",
                "wrapFactor": "0.7",
                "valueUSD": "189.286216406372063997",
                "factorUSD": "45.297854727993611256"
            },
            {
                "pool": "0xb013b68d4da85e7368a6230eed32520666100a97",
                "feeFactor": "0.9985947383062085",
                "balAndRatioFactor": "1",
                "wrapFactor": "0.7",
                "valueUSD": "0.030488650608839002",
                "factorUSD": "0.009590428913953547"
            }
        ],
        "0x1c5302aD98765D84f980a8B382EF51814A0ed2d9": [
            {
                "pool": "0x4881d85f478f47bcfd8638e5f192eba9a917daeb",
                "feeFactor": "0.9961013694701175",
                "balAndRatioFactor": "1",
                "wrapFactor": "1",
                "valueUSD": "32554.099947278727782444",
                "factorUSD": "32427.183539351420650635"
            },
            {
                "pool": "0x9869625b0c0361c3b0b42cb3f697ef4b91a1dee2",
                "feeFactor": "0.9961013694701175",
                "balAndRatioFactor": "1",
                "wrapFactor": "1",
                "valueUSD": "27654.969967891054860687",
                "factorUSD": "27547.153457671251133463"
            },
            {
                "pool": "0xcd65f38b298310fa2c8b1844ea187016f913b0c8",
                "feeFactor": "0.9961013694701175",
                "balAndRatioFactor": "0.96",
                "wrapFactor": "1",
                "valueUSD": "60771.364848261969249865",
                "factorUSD": "58113.0621599250306763"
            },
            {
                "pool": "0xdf55d0ebc4b62647ec83684eba9a49eb4bd4d384",
                "feeFactor": "0.9985947383062085",
                "balAndRatioFactor": "0.96",
                "wrapFactor": "1",
                "valueUSD": "21403.333770189482122852",
                "factorUSD": "20518.32622571788880601"
            }
        ],
        "0x5B328BB20FBf15bBecC82298db269254C3FDdb5D": [
            {
                "pool": "0x4881d85f478f47bcfd8638e5f192eba9a917daeb",
                "feeFactor": "0.9961013694701175",
                "balAndRatioFactor": "1",
                "wrapFactor": "1",
                "valueUSD": "278.683196784261417141",
                "factorUSD": "277.596713965113043033"
            }
        ],
        "0x4A4c0Ae7E2694F6F7f8A14C0A5d58967b54638ac": [
            {
                "pool": "0x4ac63d56e64c8c2cb311e9e0d4b60a7c0143bd82",
                "feeFactor": "0.9985947383062085",
                "balAndRatioFactor": "1",
                "wrapFactor": "1",
                "valueUSD": "19.393881440995159746",
                "factorUSD": "19.366627962312195351"
            },
            {
                "pool": "0x64a4579f4ac694fe6816e4fef095a7dfbfae6d1e",
                "feeFactor": "0.9985947383062085",
                "balAndRatioFactor": "1",
                "wrapFactor": "1",
                "valueUSD": "6.280235417283252523",
                "factorUSD": "6.271410043023351685"
            }
        ],
        "0x61ea25c24067738f1f587cC9E9784A7939648559": [
            {
                "pool": "0x57614d2b55d05370e56e4b3847c1c4df337ed78a",
                "feeFactor": "0.9985947383062085",
                "balAndRatioFactor": "0.64",
                "wrapFactor": "1",
                "valueUSD": "1111.645038579983345308",
                "factorUSD": "710.45304728971105315"
            }
        ],
        "0xF32B6E90A3Ff5Bee0dAD681bd488cf9A023d090d": [
            {
                "pool": "0x57614d2b55d05370e56e4b3847c1c4df337ed78a",
                "feeFactor": "0.9985947383062085",
                "balAndRatioFactor": "0.64",
                "wrapFactor": "1",
                "valueUSD": "2222.325940791997625878",
                "factorUSD": "1420.289914416821423712"
            }
        ],
        "0x52C8F15E7310D02CB7F2E20928601b86488C4397": [
            {
                "pool": "0x5bda562ceed1f5bad2ff7e4de6efab85aace6960",
                "feeFactor": "0.9985947383062085",
                "balAndRatioFactor": "1",
                "wrapFactor": "1",
                "valueUSD": "0",
                "factorUSD": "0"
            }
        ],
        "0x0338CE5020c447f7e668DC2ef778025CE398266B": [
            {
                "pool": "0x64a4579f4ac694fe6816e4fef095a7dfbfae6d1e",
                "feeFactor": "0.9985947383062085",
                "balAndRatioFactor": "1",
                "wrapFactor": "1",
                "valueUSD": "170.631960637465446806",
                "factorUSD": "170.392178079445077386"
            }
        ],
        "0x0dC437c879FaDa4Ac7E5554b0F8F1EE78343C26B": [
            {
                "pool": "0x64a4579f4ac694fe6816e4fef095a7dfbfae6d1e",
                "feeFactor": "0.9985947383062085",
                "balAndRatioFactor": "1",
                "wrapFactor": "1",
                "valueUSD": "4.68702193522966416",
                "factorUSD": "4.680435442846125404"
            },
            {
                "pool": "0xcd65f38b298310fa2c8b1844ea187016f913b0c8",
                "feeFactor": "0.9961013694701175",
                "balAndRatioFactor": "0.96",
                "wrapFactor": "1",
                "valueUSD": "150.867646105626125417",
                "factorUSD": "144.268290138765333838"
            },
            {
                "pool": "0xdf55d0ebc4b62647ec83684eba9a49eb4bd4d384",
                "feeFactor": "0.9985947383062085",
                "balAndRatioFactor": "0.96",
                "wrapFactor": "1",
                "valueUSD": "693.392924764407496634",
                "factorUSD": "664.7217851985504223"
            }
        ],
        "0x116cEb3D8d258e2A97A1f05c901Ef508809f55ec": [
            {
                "pool": "0x64a4579f4ac694fe6816e4fef095a7dfbfae6d1e",
                "feeFactor": "0.9985947383062085",
                "balAndRatioFactor": "1",
                "wrapFactor": "1",
                "valueUSD": "0.030137232618540568",
                "factorUSD": "0.030094881919984849"
            },
            {
                "pool": "0x870085d178dae004522126bf6d5e23949eeded71",
                "feeFactor": "0.9961013694701175",
                "balAndRatioFactor": "1",
                "wrapFactor": "1",
                "valueUSD": "1.525407660621308555",
                "factorUSD": "1.519460659745093678"
            },
            {
                "pool": "0x9344b7f5fcb8a456716cd6c7059dfeac370f5fd7",
                "feeFactor": "0.9985947383062085",
                "balAndRatioFactor": "0.875397329942784487",
                "wrapFactor": "1",
                "valueUSD": "1.069878874754160606",
                "factorUSD": "0.935252985627659064"
            },
            {
                "pool": "0xc25e1181cd0213cc321a7d34d641897240e484dd",
                "feeFactor": "0.9943907906910809",
                "balAndRatioFactor": "1",
                "wrapFactor": "0.1",
                "valueUSD": "1.535213855218400689",
                "factorUSD": "0.152660251937052805"
            },
            {
                "pool": "0xcd65f38b298310fa2c8b1844ea187016f913b0c8",
                "feeFactor": "0.9961013694701175",
                "balAndRatioFactor": "0.96",
                "wrapFactor": "1",
                "valueUSD": "23.313371542951094082",
                "factorUSD": "22.293582068063281019"
            },
            {
                "pool": "0xf73f3a1e15fcec85356048c95f2d6ae54ab1a535",
                "feeFactor": "0.9961013694701175",
                "balAndRatioFactor": "1",
                "wrapFactor": "1",
                "valueUSD": "12.763960407434235916",
                "factorUSD": "12.714198441707601317"
            }
        ],
        "0x2418e5454B75e18a2C7a849aeCCFCD03f67731C3": [
            {
                "pool": "0x64a4579f4ac694fe6816e4fef095a7dfbfae6d1e",
                "feeFactor": "0.9985947383062085",
                "balAndRatioFactor": "1",
                "wrapFactor": "1",
                "valueUSD": "27713.544493827399422973",
                "factorUSD": "27674.599711351037405469"
            },
            {
                "pool": "0x65b0e9418e102a880c92790f001a9c5810b0ef32",
                "feeFactor": "0.9993751952718163",
                "balAndRatioFactor": "0.96",
                "wrapFactor": "1",
                "valueUSD": "90.010528207780991139",
                "factorUSD": "86.356117636003638984"
            },
            {
                "pool": "0x82ee4c435fd3bd9eff03e35f232dab419f89300d",
                "feeFactor": "0.9985947383062085",
                "balAndRatioFactor": "1",
                "wrapFactor": "1",
                "valueUSD": "17932.699850841669016989",
                "factorUSD": "17907.499714675020673779"
            },
            {
                "pool": "0x852c807d9853afe0eb71644d1a1693def83f66cf",
                "feeFactor": "0.9985947383062085",
                "balAndRatioFactor": "0.64",
                "wrapFactor": "1",
                "valueUSD": "71829.470013733027414499",
                "factorUSD": "45906.259719063925236241"
            },
            {
                "pool": "0xc4f0752c7de35f7d696b2cbf2447795a6c824701",
                "feeFactor": "0.9985947383062085",
                "balAndRatioFactor": "0.96",
                "wrapFactor": "1",
                "valueUSD": "81.826152350170966572",
                "factorUSD": "78.442718585014007031"
            },
            {
                "pool": "0xdf55d0ebc4b62647ec83684eba9a49eb4bd4d384",
                "feeFactor": "0.9985947383062085",
                "balAndRatioFactor": "0.96",
                "wrapFactor": "1",
                "valueUSD": "13138.934749806433184126",
                "factorUSD": "12595.652263781092029651"
            }
        ],
        "0xb08794f9eC5b5D19E88673fC8763243c630E828d": [
            {
                "pool": "0x64a4579f4ac694fe6816e4fef095a7dfbfae6d1e",
                "feeFactor": "0.9985947383062085",
                "balAndRatioFactor": "1",
                "wrapFactor": "1",
                "valueUSD": "66.484642059472387027",
                "factorUSD": "66.391213738760771193"
            }
        ],
        "0xb0a4E99371dfb0734F002ae274933b4888F618ef": [
            {
                "pool": "0x64a4579f4ac694fe6816e4fef095a7dfbfae6d1e",
                "feeFactor": "0.9985947383062085",
                "balAndRatioFactor": "1",
                "wrapFactor": "1",
                "valueUSD": "80586.258174950493430629",
                "factorUSD": "80473.01339329124330622"
            }
        ],
        "0xE380c7FE194cF2afE3477044D3c6F5D4f82343a7": [
            {
                "pool": "0x64a4579f4ac694fe6816e4fef095a7dfbfae6d1e",
                "feeFactor": "0.9985947383062085",
                "balAndRatioFactor": "1",
                "wrapFactor": "1",
                "valueUSD": "1.230444528763456257",
                "factorUSD": "1.228715432200849638"
            },
            {
                "pool": "0x79670b0cb738a0bd826bc7709bc363c6b554690b",
                "feeFactor": "0.9961013694701175",
                "balAndRatioFactor": "1",
                "wrapFactor": "1",
                "valueUSD": "716.459260280271509101",
                "factorUSD": "713.666050334725810202"
            },
            {
                "pool": "0x870085d178dae004522126bf6d5e23949eeded71",
                "feeFactor": "0.9961013694701175",
                "balAndRatioFactor": "1",
                "wrapFactor": "1",
                "valueUSD": "1.090131779342848329",
                "factorUSD": "1.085881758306307168"
            },
            {
                "pool": "0x9869625b0c0361c3b0b42cb3f697ef4b91a1dee2",
                "feeFactor": "0.9961013694701175",
                "balAndRatioFactor": "1",
                "wrapFactor": "1",
                "valueUSD": "3825.335226722969606889",
                "factorUSD": "3810.421658021032442616"
            },
            {
                "pool": "0xcd65f38b298310fa2c8b1844ea187016f913b0c8",
                "feeFactor": "0.9961013694701175",
                "balAndRatioFactor": "0.96",
                "wrapFactor": "1",
                "valueUSD": "3616.271853099363503152",
                "factorUSD": "3458.086411438574938961"
            }
        ],
        "0xea7A42D29c7Ce1ed2c7F69e39152Cf1840b0A964": [
            {
                "pool": "0x64a4579f4ac694fe6816e4fef095a7dfbfae6d1e",
                "feeFactor": "0.9985947383062085",
                "balAndRatioFactor": "1",
                "wrapFactor": "1",
                "valueUSD": "2394.028477209199287899",
                "factorUSD": "2390.664240696331200662"
            },
            {
                "pool": "0x870085d178dae004522126bf6d5e23949eeded71",
                "feeFactor": "0.9961013694701175",
                "balAndRatioFactor": "1",
                "wrapFactor": "1",
                "valueUSD": "1123.000023852755386809",
                "factorUSD": "1118.621861674704258936"
            },
            {
                "pool": "0xcd65f38b298310fa2c8b1844ea187016f913b0c8",
                "feeFactor": "0.9961013694701175",
                "balAndRatioFactor": "0.96",
                "wrapFactor": "1",
                "valueUSD": "722.286713476793699649",
                "factorUSD": "690.691953066532394855"
            }
        ],
        "0xea96EDdF997B45E22dd7cdB0EE45744f53e33693": [
            {
                "pool": "0x64a4579f4ac694fe6816e4fef095a7dfbfae6d1e",
                "feeFactor": "0.9985947383062085",
                "balAndRatioFactor": "1",
                "wrapFactor": "1",
                "valueUSD": "241.995190833167822178",
                "factorUSD": "241.655124261408207249"
            },
            {
                "pool": "0x870085d178dae004522126bf6d5e23949eeded71",
                "feeFactor": "0.9961013694701175",
                "balAndRatioFactor": "1",
                "wrapFactor": "1",
                "valueUSD": "148.930059161300522332",
                "factorUSD": "148.349435885837069203"
            }
        ],
        "0x6626528DE0c75Ccc7A0d24F2D24b99060f74EdEe": [
            {
                "pool": "0x65b0e9418e102a880c92790f001a9c5810b0ef32",
                "feeFactor": "0.9993751952718163",
                "balAndRatioFactor": "0.96",
                "wrapFactor": "1",
                "valueUSD": "81827.752916164592515032",
                "factorUSD": "78505.561487276088318519"
            }
        ],
        "0x081aB2fa7f8F4d9E89F017ca1195b0CC75245AeE": [
            {
                "pool": "0x6e2b58dfce2b39495e28881b616e32df2dae8bdd",
                "feeFactor": "0.569782824730923",
                "balAndRatioFactor": "1",
                "wrapFactor": "1",
                "valueUSD": "0.002008761938243264",
                "factorUSD": "0.00114455805138421"
            }
        ],
        "0x15eCd31318fa645B6496F1f21b22Ebfe3AD0c865": [
            {
                "pool": "0x79670b0cb738a0bd826bc7709bc363c6b554690b",
                "feeFactor": "0.9961013694701175",
                "balAndRatioFactor": "1",
                "wrapFactor": "1",
                "valueUSD": "94.375481421458955806",
                "factorUSD": "94.007546288316897243"
            },
            {
                "pool": "0x8c7197df2d8859f5a2889da80a21f8ea6e4cae51",
                "feeFactor": "0.9961013694701175",
                "balAndRatioFactor": "0.875397329942784487",
                "wrapFactor": "1",
                "valueUSD": "52.560945326690274877",
                "factorUSD": "45.832328536243695924"
            }
        ],
        "0x9C7B84BE5D69BB41a718A4aF921E44730a277F90": [
            {
                "pool": "0x79670b0cb738a0bd826bc7709bc363c6b554690b",
                "feeFactor": "0.9961013694701175",
                "balAndRatioFactor": "1",
                "wrapFactor": "1",
                "valueUSD": "59.452282575828721455",
                "factorUSD": "59.220500091907394204"
            }
        ],
        "0xa2BfA5a2EA2E032A82E948dAD4310B069a9C8ED5": [
            {
                "pool": "0x79670b0cb738a0bd826bc7709bc363c6b554690b",
                "feeFactor": "0.9961013694701175",
                "balAndRatioFactor": "1",
                "wrapFactor": "1",
                "valueUSD": "0.103875571408553093",
                "factorUSD": "0.103470598934550718"
            },
            {
                "pool": "0x82ee4c435fd3bd9eff03e35f232dab419f89300d",
                "feeFactor": "0.9985947383062085",
                "balAndRatioFactor": "1",
                "wrapFactor": "1",
                "valueUSD": "0.089727052222404891",
                "factorUSD": "0.089600962233019916"
            },
            {
                "pool": "0x852c807d9853afe0eb71644d1a1693def83f66cf",
                "feeFactor": "0.9985947383062085",
                "balAndRatioFactor": "0.64",
                "wrapFactor": "1",
                "valueUSD": "0.053949187380358978",
                "factorUSD": "0.034478959778510195"
            },
            {
                "pool": "0x8c7197df2d8859f5a2889da80a21f8ea6e4cae51",
                "feeFactor": "0.9961013694701175",
                "balAndRatioFactor": "0.875397329942784487",
                "wrapFactor": "1",
                "valueUSD": "0.02210483949578014",
                "factorUSD": "0.019275076955228842"
            },
            {
                "pool": "0xbf511ad7c4426980e27f6b84a2e3899c565b5c2b",
                "feeFactor": "0.9961013694701175",
                "balAndRatioFactor": "0.64",
                "wrapFactor": "1",
                "valueUSD": "0.050275347555912828",
                "factorUSD": "0.032050779232659771"
            },
            {
                "pool": "0xcd65f38b298310fa2c8b1844ea187016f913b0c8",
                "feeFactor": "0.9961013694701175",
                "balAndRatioFactor": "0.96",
                "wrapFactor": "1",
                "valueUSD": "0.050620858818935369",
                "factorUSD": "0.048406566521563196"
            }
        ],
        "0xCa42438C22a1BD26d48CC86aC669F23ead65e2c4": [
            {
                "pool": "0x79670b0cb738a0bd826bc7709bc363c6b554690b",
                "feeFactor": "0.9961013694701175",
                "balAndRatioFactor": "1",
                "wrapFactor": "1",
                "valueUSD": "0.022318778962160347",
                "factorUSD": "0.02223176628910877"
            },
            {
                "pool": "0x82ee4c435fd3bd9eff03e35f232dab419f89300d",
                "feeFactor": "0.9985947383062085",
                "balAndRatioFactor": "1",
                "wrapFactor": "1",
                "valueUSD": "0.034318366006514405",
                "factorUSD": "0.034270139721371934"
            },
            {
                "pool": "0x852c807d9853afe0eb71644d1a1693def83f66cf",
                "feeFactor": "0.9985947383062085",
                "balAndRatioFactor": "0.64",
                "wrapFactor": "1",
                "valueUSD": "0.038971044737195442",
                "factorUSD": "0.024906419341349904"
            },
            {
                "pool": "0x8c7197df2d8859f5a2889da80a21f8ea6e4cae51",
                "feeFactor": "0.9961013694701175",
                "balAndRatioFactor": "0.875397329942784487",
                "wrapFactor": "1",
                "valueUSD": "0.025169794206425145",
                "factorUSD": "0.021947669892320811"
            },
            {
                "pool": "0xbf511ad7c4426980e27f6b84a2e3899c565b5c2b",
                "feeFactor": "0.9961013694701175",
                "balAndRatioFactor": "0.64",
                "wrapFactor": "1",
                "valueUSD": "0.009957104266447115",
                "factorUSD": "0.006347702525289421"
            },
            {
                "pool": "0xcd65f38b298310fa2c8b1844ea187016f913b0c8",
                "feeFactor": "0.9961013694701175",
                "balAndRatioFactor": "0.96",
                "wrapFactor": "1",
                "valueUSD": "0.038298927405178007",
                "factorUSD": "0.03662362947603305"
            }
        ],
        "0xED15f09337E478359C20107FC00fd6B295F9E12e": [
            {
                "pool": "0x796de89cc875c06805228a1404d53e0d27a35254",
                "feeFactor": "0.9985947383062085",
                "balAndRatioFactor": "0.888888888888888887",
                "wrapFactor": "1",
                "valueUSD": "0",
                "factorUSD": "0"
            }
        ],
        "0xB3DA1b8a363b04D7e628C8f40E55368156949e3e": [
            {
                "pool": "0x80d4bf4686c0ebd3fdeda13a374c227d69081f5c",
                "feeFactor": "0.9943907906910809",
                "balAndRatioFactor": "0.994198017701192493",
                "wrapFactor": "0.887158351409978308",
                "valueUSD": "7.587398969396763021",
                "factorUSD": "5.619467136048220975"
            }
        ],
        "0xC2C79Da7B83dafC2Af95F9d3CD2BE48934b9fD8B": [
            {
                "pool": "0x81dc98714e8126a3ccfd1118c7feefc991e7f39f",
                "feeFactor": "0.9975031223974601",
                "balAndRatioFactor": "1",
                "wrapFactor": "1",
                "valueUSD": "0.200808446907447608",
                "factorUSD": "0.200307052793963579"
            }
        ],
        "0x2c640AC98E293Daa246F98D2828E328A06FA6936": [
            {
                "pool": "0x82ee4c435fd3bd9eff03e35f232dab419f89300d",
                "feeFactor": "0.9985947383062085",
                "balAndRatioFactor": "1",
                "wrapFactor": "1",
                "valueUSD": "4.518183333331762526",
                "factorUSD": "4.511834103367904208"
            }
        ],
        "0x5D6FeAE7cAFB7a6472624272971b20224B088680": [
            {
                "pool": "0x82ee4c435fd3bd9eff03e35f232dab419f89300d",
                "feeFactor": "0.9985947383062085",
                "balAndRatioFactor": "1",
                "wrapFactor": "1",
                "valueUSD": "8893.073208645192650112",
                "factorUSD": "8880.576113525000097008"
            }
        ],
        "0xc36Ea7b3f0BadC0f4e3C505f84068D6bDB297eA7": [
            {
                "pool": "0x82ee4c435fd3bd9eff03e35f232dab419f89300d",
                "feeFactor": "0.9985947383062085",
                "balAndRatioFactor": "1",
                "wrapFactor": "1",
                "valueUSD": "408.672024537900145085",
                "factorUSD": "408.097733396492814077"
            }
        ],
        "0x9f2655A391d89E27A7624328D0c0d0c9C7be924d": [
            {
                "pool": "0x84895e3f66741e83798e7489ef2ae653efa12a78",
                "feeFactor": "0.569782824730923",
                "balAndRatioFactor": "1",
                "wrapFactor": "1",
                "valueUSD": "2.028849557625697852",
                "factorUSD": "1.156003631898053662"
            }
        ],
        "0x0eE0B4D2Ff7e7b02c011178D9440D05F50cE2EE3": [
            {
                "pool": "0x852c807d9853afe0eb71644d1a1693def83f66cf",
                "feeFactor": "0.9985947383062085",
                "balAndRatioFactor": "0.64",
                "wrapFactor": "1",
                "valueUSD": "0.87215476328652284",
                "factorUSD": "0.557394660868235838"
            },
            {
                "pool": "0xcd65f38b298310fa2c8b1844ea187016f913b0c8",
                "feeFactor": "0.9961013694701175",
                "balAndRatioFactor": "0.96",
                "wrapFactor": "1",
                "valueUSD": "0.791390667263400716",
                "factorUSD": "0.756773114349065798"
            }
        ],
        "0xb90829B1e57C04A77C5740638a6D8EbC32B67e92": [
            {
                "pool": "0x852c807d9853afe0eb71644d1a1693def83f66cf",
                "feeFactor": "0.9985947383062085",
                "balAndRatioFactor": "0.64",
                "wrapFactor": "1",
                "valueUSD": "493.448172959156625535",
                "factorUSD": "315.36303945204846083"
            }
        ],
        "0xb4633912c7374cd94D8917a167449e23b46d0AD1": [
            {
                "pool": "0x870085d178dae004522126bf6d5e23949eeded71",
                "feeFactor": "0.9961013694701175",
                "balAndRatioFactor": "1",
                "wrapFactor": "1",
                "valueUSD": "0.164910559717625448",
                "factorUSD": "0.164267634374810302"
            }
        ],
        "0xccb78FE2dAc3349CA4415815A74e960FDae53355": [
            {
                "pool": "0x870085d178dae004522126bf6d5e23949eeded71",
                "feeFactor": "0.9961013694701175",
                "balAndRatioFactor": "1",
                "wrapFactor": "1",
                "valueUSD": "13671.64127506081099819",
                "factorUSD": "13618.340596992257210675"
            },
            {
                "pool": "0xcd65f38b298310fa2c8b1844ea187016f913b0c8",
                "feeFactor": "0.9961013694701175",
                "balAndRatioFactor": "0.96",
                "wrapFactor": "1",
                "valueUSD": "12954.915806729718527051",
                "factorUSD": "12388.233001395402882768"
            }
        ],
        "0xf4ADC8369e83D6A599e51438D44B5e53A412f807": [
            {
                "pool": "0x870085d178dae004522126bf6d5e23949eeded71",
                "feeFactor": "0.9961013694701175",
                "balAndRatioFactor": "1",
                "wrapFactor": "1",
                "valueUSD": "195395.692463224721724664",
                "factorUSD": "194633.916851180061916162"
            },
            {
                "pool": "0xcd65f38b298310fa2c8b1844ea187016f913b0c8",
                "feeFactor": "0.9961013694701175",
                "balAndRatioFactor": "0.96",
                "wrapFactor": "1",
                "valueUSD": "4566.024677489957859051",
                "factorUSD": "4366.294496910814668934"
            }
        ],
        "0x9d6EbCB3a6c96E9C52219c2cd92482F238B84826": [
            {
                "pool": "0x87a1840d49006586343dfec09dc7fc3708fed300",
                "feeFactor": "0.9985947383062085",
                "balAndRatioFactor": "1",
                "wrapFactor": "1",
                "valueUSD": "0",
                "factorUSD": "0"
            }
        ],
        "0xAc7995f3cEeBe1063E64da0dEfAfb2B2051E3CD5": [
            {
                "pool": "0x8c7197df2d8859f5a2889da80a21f8ea6e4cae51",
                "feeFactor": "0.9961013694701175",
                "balAndRatioFactor": "0.875397329942784487",
                "wrapFactor": "1",
                "valueUSD": "2587.097029079922180301",
                "factorUSD": "2255.908455507176492809"
            },
            {
                "pool": "0xa607473429303028686a6fa2d0b8eca5c0d86525",
                "feeFactor": "0.9961013694701175",
                "balAndRatioFactor": "1",
                "wrapFactor": "1",
                "valueUSD": "2069.45069607334500463",
                "factorUSD": "2061.382672409546871132"
            }
        ],
        "0x9c754e1444fC2D7394cCEbb339670D9fEa573E4A": [
            {
                "pool": "0x9344b7f5fcb8a456716cd6c7059dfeac370f5fd7",
                "feeFactor": "0.9985947383062085",
                "balAndRatioFactor": "0.875397329942784487",
                "wrapFactor": "1",
                "valueUSD": "1775.448287349981427351",
                "factorUSD": "1552.038600587506982348"
            }
        ],
        "0x67AFB2288621c20E4872F6FBAeb05Ab566CeD31d": [
            {
                "pool": "0x9869625b0c0361c3b0b42cb3f697ef4b91a1dee2",
                "feeFactor": "0.9961013694701175",
                "balAndRatioFactor": "1",
                "wrapFactor": "1",
                "valueUSD": "859.756685682343150519",
                "factorUSD": "856.404812019271375041"
            },
            {
                "pool": "0x9c7f91b03f2332bcebb0b57c9891e8d26b8e3435",
                "feeFactor": "0.9844964370054085",
                "balAndRatioFactor": "0.785714285714285714",
                "wrapFactor": "1",
                "valueUSD": "614.728398555675111168",
                "factorUSD": "475.512649938937954669"
            },
            {
                "pool": "0xcd65f38b298310fa2c8b1844ea187016f913b0c8",
                "feeFactor": "0.9961013694701175",
                "balAndRatioFactor": "0.96",
                "wrapFactor": "1",
                "valueUSD": "697.33268232279781487",
                "factorUSD": "666.829478244488928561"
            }
        ],
        "0xb5F91Aa1b639d6dA300bCcB87387007D99023302": [
            {
                "pool": "0x9869625b0c0361c3b0b42cb3f697ef4b91a1dee2",
                "feeFactor": "0.9961013694701175",
                "balAndRatioFactor": "1",
                "wrapFactor": "1",
                "valueUSD": "496.196640842472006047",
                "factorUSD": "494.262153469658402869"
            }
        ],
        "0x167F897440cfD5227F22349779841F83DdDA126a": [
            {
                "pool": "0xa59cf736fb8dec59a9171c62060e43208af0e07f",
                "feeFactor": "0.9985947383062085",
                "balAndRatioFactor": "0.19",
                "wrapFactor": "1",
                "valueUSD": "17.117051004258060063",
                "factorUSD": "3.247669442952509168"
            }
        ],
        "0x169833EBB85FBD3cb67eeC73Ed02f738c0017951": [
            {
                "pool": "0xa59cf736fb8dec59a9171c62060e43208af0e07f",
                "feeFactor": "0.9985947383062085",
                "balAndRatioFactor": "0.19",
                "wrapFactor": "1",
                "valueUSD": "29.980616629657540536",
                "factorUSD": "5.68831234333481053"
            }
        ],
        "0x3c9B3d0b4A42DAA68c01F34fd1DCF8615eA1fEe4": [
            {
                "pool": "0xa59cf736fb8dec59a9171c62060e43208af0e07f",
                "feeFactor": "0.9985947383062085",
                "balAndRatioFactor": "0.19",
                "wrapFactor": "1",
                "valueUSD": "112.829366397417566823",
                "factorUSD": "21.407454206068056911"
            }
        ],
        "0xA3c7a8eAF23D2dd89ed81E19a5de8C84E26B0c4E": [
            {
                "pool": "0xa59cf736fb8dec59a9171c62060e43208af0e07f",
                "feeFactor": "0.9985947383062085",
                "balAndRatioFactor": "0.19",
                "wrapFactor": "1",
                "valueUSD": "12.560318180154589773",
                "factorUSD": "2.383106852769295257"
            }
        ],
        "0xd4DC77165051bc2AeAdFf2C8A681B87163E47820": [
            {
                "pool": "0xa59cf736fb8dec59a9171c62060e43208af0e07f",
                "feeFactor": "0.9985947383062085",
                "balAndRatioFactor": "0.19",
                "wrapFactor": "1",
                "valueUSD": "164.816612707966380679",
                "factorUSD": "31.271150424769207174"
            },
            {
                "pool": "0xcd65f38b298310fa2c8b1844ea187016f913b0c8",
                "feeFactor": "0.9961013694701175",
                "balAndRatioFactor": "0.96",
                "wrapFactor": "1",
                "valueUSD": "442.583119032174792159",
                "factorUSD": "423.223344933413121579"
            }
        ],
        "0xe546E60D8cc8a85cF103d7B174bf1692DFA3f838": [
            {
                "pool": "0xa59cf736fb8dec59a9171c62060e43208af0e07f",
                "feeFactor": "0.9985947383062085",
                "balAndRatioFactor": "0.19",
                "wrapFactor": "1",
                "valueUSD": "1.66551384712165602",
                "factorUSD": "0.316002939219245162"
            }
        ],
        "0xEB23924B746A43Fa1143D93DfAC712b9Dc3fFfC8": [
            {
                "pool": "0xa59cf736fb8dec59a9171c62060e43208af0e07f",
                "feeFactor": "0.9985947383062085",
                "balAndRatioFactor": "0.19",
                "wrapFactor": "1",
                "valueUSD": "7442.220247077740742109",
                "factorUSD": "1412.034776209074947299"
            }
        ],
        "0xA7AAFFdEDf9b3A0bc0a0EFafB109a44f316C423C": [
            {
                "pool": "0xaf9530f351c14901d7e1030a51f5e87519c9e3a2",
                "feeFactor": "0.9940117514610743",
                "balAndRatioFactor": "1",
                "wrapFactor": "0.1",
                "valueUSD": "1.834567834248238204",
                "factorUSD": "0.072943279443809644"
            }
        ],
        "0x099C50BeE65EeCDcd209C38f1207fc334ea5eaB1": [
            {
                "pool": "0xbf511ad7c4426980e27f6b84a2e3899c565b5c2b",
                "feeFactor": "0.9961013694701175",
                "balAndRatioFactor": "0.64",
                "wrapFactor": "1",
                "valueUSD": "204.647413241181953797",
                "factorUSD": "130.463723896357377055"
            }
        ],
        "0x78E87757861185Ec5e8C0EF6BF0C69Fa7832df6C": [
            {
                "pool": "0xbf511ad7c4426980e27f6b84a2e3899c565b5c2b",
                "feeFactor": "0.9961013694701175",
                "balAndRatioFactor": "0.64",
                "wrapFactor": "1",
                "valueUSD": "65.058964040720996474",
                "factorUSD": "41.475406833452360872"
            },
            {
                "pool": "0xcd65f38b298310fa2c8b1844ea187016f913b0c8",
                "feeFactor": "0.9961013694701175",
                "balAndRatioFactor": "0.96",
                "wrapFactor": "1",
                "valueUSD": "865.778159289159528768",
                "factorUSD": "827.906697720239363774"
            }
        ],
        "0xc70c7f140d095381bFe45C9de8F16F7548547832": [
            {
                "pool": "0xbf511ad7c4426980e27f6b84a2e3899c565b5c2b",
                "feeFactor": "0.9961013694701175",
                "balAndRatioFactor": "0.64",
                "wrapFactor": "1",
                "valueUSD": "65.096944255422962858",
                "factorUSD": "41.499619405533895467"
            }
        ],
        "0x0f820E108421D97432BeF1696205aC6F9f79EACe": [
            {
                "pool": "0xc25e1181cd0213cc321a7d34d641897240e484dd",
                "feeFactor": "0.9943907906910809",
                "balAndRatioFactor": "1",
                "wrapFactor": "0.1",
                "valueUSD": "15.406051810340513218",
                "factorUSD": "1.531963604111226125"
            }
        ],
        "0x25a9b8B7Ff067DF3087fa015F91654360c26006C": [
            {
                "pool": "0xc25e1181cd0213cc321a7d34d641897240e484dd",
                "feeFactor": "0.9943907906910809",
                "balAndRatioFactor": "1",
                "wrapFactor": "0.1",
                "valueUSD": "231.809496865401270539",
                "factorUSD": "23.05092288776880088"
            },
            {
                "pool": "0xcd65f38b298310fa2c8b1844ea187016f913b0c8",
                "feeFactor": "0.9961013694701175",
                "balAndRatioFactor": "0.96",
                "wrapFactor": "1",
                "valueUSD": "135.77211525833074702",
                "factorUSD": "129.83307834689077743"
            }
        ],
        "0x6EAA11eec98c663ba096593cc779217A7e20665a": [
            {
                "pool": "0xc25e1181cd0213cc321a7d34d641897240e484dd",
                "feeFactor": "0.9943907906910809",
                "balAndRatioFactor": "1",
                "wrapFactor": "0.1",
                "valueUSD": "2007.235705985713906541",
                "factorUSD": "199.597670077850403844"
            }
        ],
        "0x8D071fa6905E1fB872903603A6239947C03fd450": [
            {
                "pool": "0xc25e1181cd0213cc321a7d34d641897240e484dd",
                "feeFactor": "0.9943907906910809",
                "balAndRatioFactor": "1",
                "wrapFactor": "0.1",
                "valueUSD": "9.005431794532712346",
                "factorUSD": "0.895491844267998342"
            }
        ],
        "0xbe09DE9f8caeE25C422459C1E13D6CaEd78683fD": [
            {
                "pool": "0xc25e1181cd0213cc321a7d34d641897240e484dd",
                "feeFactor": "0.9943907906910809",
                "balAndRatioFactor": "1",
                "wrapFactor": "0.1",
                "valueUSD": "102.277623133130194533",
                "factorUSD": "10.170392653735772115"
            }
        ],
        "0xDdf900f5CaB4D248D0306A36e9bd5f78991e65B1": [
            {
                "pool": "0xc25e1181cd0213cc321a7d34d641897240e484dd",
                "feeFactor": "0.9943907906910809",
                "balAndRatioFactor": "1",
                "wrapFactor": "0.1",
                "valueUSD": "66.337450368790281213",
                "factorUSD": "6.596534972465170398"
            }
        ],
        "0xAD4945c9ABc22e207f99e763a9F8854539a1FE5b": [
            {
                "pool": "0xc332e2e2db50fd88216d4a53ef5d92d8843cc01c",
                "feeFactor": "0.9961013694701175",
                "balAndRatioFactor": "0.0784",
                "wrapFactor": "1",
                "valueUSD": "0",
                "factorUSD": "0"
            }
        ],
        "0xDeBdaF2390372E715C7F396559d1BbE1b69B53AD": [
            {
                "pool": "0xc63e533e3cd13acebd3fb41f5cd4b3339102e7e6",
                "feeFactor": "0.9985947383062085",
                "balAndRatioFactor": "1",
                "wrapFactor": "1",
                "valueUSD": "5.608693204708771301",
                "factorUSD": "5.600811522995965376"
            }
        ],
        "0x0a1f2e1a4585bbf5E54a894FffA74133654BfaDC": [
            {
                "pool": "0xcd65f38b298310fa2c8b1844ea187016f913b0c8",
                "feeFactor": "0.9961013694701175",
                "balAndRatioFactor": "0.96",
                "wrapFactor": "1",
                "valueUSD": "339.779333056362463922",
                "factorUSD": "324.916472616082382478"
            }
        ],
        "0x12db4993126eBcd26E8dFeF76Fe3aE539b47f25b": [
            {
                "pool": "0xcd65f38b298310fa2c8b1844ea187016f913b0c8",
                "feeFactor": "0.9961013694701175",
                "balAndRatioFactor": "0.96",
                "wrapFactor": "1",
                "valueUSD": "14592.793356604111389966",
                "factorUSD": "13954.465389031476554301"
            }
        ],
        "0x18fEe6e511646B8ea2e4964277574F637Bc03f3b": [
            {
                "pool": "0xcd65f38b298310fa2c8b1844ea187016f913b0c8",
                "feeFactor": "0.9961013694701175",
                "balAndRatioFactor": "0.96",
                "wrapFactor": "1",
                "valueUSD": "3219.578345724787338914",
                "factorUSD": "3078.745343321084244933"
            }
        ],
        "0x1c85d6Ae1336D0e4E3F165bbfA9641bfA04CeDb1": [
            {
                "pool": "0xcd65f38b298310fa2c8b1844ea187016f913b0c8",
                "feeFactor": "0.9961013694701175",
                "balAndRatioFactor": "0.96",
                "wrapFactor": "1",
                "valueUSD": "3.426385847249485551",
                "factorUSD": "3.276506529387111734"
            }
        ],
        "0x26b350F462Ae30EC1c48c36ba944AB66F06dAFee": [
            {
                "pool": "0xcd65f38b298310fa2c8b1844ea187016f913b0c8",
                "feeFactor": "0.9961013694701175",
                "balAndRatioFactor": "0.96",
                "wrapFactor": "1",
                "valueUSD": "76.820308764620629165",
                "factorUSD": "73.459982173013643823"
            }
        ],
        "0x4FfD0A59a26cB2Aa76D403215e4cC2845C053994": [
            {
                "pool": "0xcd65f38b298310fa2c8b1844ea187016f913b0c8",
                "feeFactor": "0.9961013694701175",
                "balAndRatioFactor": "0.96",
                "wrapFactor": "1",
                "valueUSD": "1.657038083849860366",
                "factorUSD": "1.58455478840350589"
            }
        ],
        "0x6a1afc8a229d820015361Da64819e64E6A0258F9": [
            {
                "pool": "0xcd65f38b298310fa2c8b1844ea187016f913b0c8",
                "feeFactor": "0.9961013694701175",
                "balAndRatioFactor": "0.96",
                "wrapFactor": "1",
                "valueUSD": "1.651989771347479312",
                "factorUSD": "1.579727302646256402"
            }
        ],
        "0x751f556a157f8cb70d5f37086664b437F339D914": [
            {
                "pool": "0xcd65f38b298310fa2c8b1844ea187016f913b0c8",
                "feeFactor": "0.9961013694701175",
                "balAndRatioFactor": "0.96",
                "wrapFactor": "1",
                "valueUSD": "22.594472628663629642",
                "factorUSD": "21.606129722752250028"
            }
        ],
        "0x7A3ba9cee390C16eC95E65C2c65961E72F8f5877": [
            {
                "pool": "0xcd65f38b298310fa2c8b1844ea187016f913b0c8",
                "feeFactor": "0.9961013694701175",
                "balAndRatioFactor": "0.96",
                "wrapFactor": "1",
                "valueUSD": "158.166868174344221494",
                "factorUSD": "151.248224633533269462"
            }
        ],
        "0x7Ad5583713ca971F2aE1E0a894486a9406179eca": [
            {
                "pool": "0xcd65f38b298310fa2c8b1844ea187016f913b0c8",
                "feeFactor": "0.9961013694701175",
                "balAndRatioFactor": "0.96",
                "wrapFactor": "1",
                "valueUSD": "4.13413517642173055",
                "factorUSD": "3.953297002375940752"
            }
        ],
        "0x9BDbdb4A8f7f816C87a67F5281484ED902C6b942": [
            {
                "pool": "0xcd65f38b298310fa2c8b1844ea187016f913b0c8",
                "feeFactor": "0.9961013694701175",
                "balAndRatioFactor": "0.96",
                "wrapFactor": "1",
                "valueUSD": "0.039705088426738918",
                "factorUSD": "0.037968281238534479"
            }
        ],
        "0xce66C6A88bD7BEc215Aa04FDa4CF7C81055521D0": [
            {
                "pool": "0xcd65f38b298310fa2c8b1844ea187016f913b0c8",
                "feeFactor": "0.9961013694701175",
                "balAndRatioFactor": "0.96",
                "wrapFactor": "1",
                "valueUSD": "5360.884537077978608399",
                "factorUSD": "5126.385051796369332421"
            }
        ],
        "0xd61b13A235EE8cfdef89337bb425D9323895c7Ea": [
            {
                "pool": "0xcd65f38b298310fa2c8b1844ea187016f913b0c8",
                "feeFactor": "0.9961013694701175",
                "balAndRatioFactor": "0.96",
                "wrapFactor": "1",
                "valueUSD": "1.068641693936439333",
                "factorUSD": "1.021896436610835245"
            }
        ],
        "0xdec0DED0606B7d0560ADEBD6C3a919a671dB4D66": [
            {
                "pool": "0xcd65f38b298310fa2c8b1844ea187016f913b0c8",
                "feeFactor": "0.9961013694701175",
                "balAndRatioFactor": "0.96",
                "wrapFactor": "1",
                "valueUSD": "6333.876732419082938261",
                "factorUSD": "6056.815955728859031628"
            }
        ],
        "0xe5F470E376554fB613A43FDe223e40a3bb338765": [
            {
                "pool": "0xcd65f38b298310fa2c8b1844ea187016f913b0c8",
                "feeFactor": "0.9961013694701175",
                "balAndRatioFactor": "0.96",
                "wrapFactor": "1",
                "valueUSD": "6.160399290472723659",
                "factorUSD": "5.890926882933715399"
            }
        ],
        "0xF3783A4f80B2e06A6addc58D4d69B3a04aC32971": [
            {
                "pool": "0xcd65f38b298310fa2c8b1844ea187016f913b0c8",
                "feeFactor": "0.9961013694701175",
                "balAndRatioFactor": "0.96",
                "wrapFactor": "1",
                "valueUSD": "58.244198867642998835",
                "factorUSD": "55.69644120551909578"
            }
        ],
        "0x09Fa38EBa245bb68354B8950FA2fe71f02863393": [
            {
                "pool": "0xd588600b00a5783617fabb01fe75e19bbd125ea3",
                "feeFactor": "0.9961013694701175",
                "balAndRatioFactor": "0.911111111111111109",
                "wrapFactor": "1",
                "valueUSD": "98.230968989505561452",
                "factorUSD": "89.150402491727744067"
            },
            {
                "pool": "0xf73f3a1e15fcec85356048c95f2d6ae54ab1a535",
                "feeFactor": "0.9961013694701175",
                "balAndRatioFactor": "1",
                "wrapFactor": "1",
                "valueUSD": "19.089132169102886357",
                "factorUSD": "19.014710695639459675"
            }
        ],
        "0x5c41E116C162923aF27aa86Ba6dC2299f0Da313c": [
            {
                "pool": "0xdb2e934d29e633ddbb23c7a01bf93fab41fdc58d",
                "feeFactor": "0.9985947383062085",
                "balAndRatioFactor": "0.888888888888888888",
                "wrapFactor": "1",
                "valueUSD": "0",
                "factorUSD": "0"
            }
        ],
        "0x4E0985E556069B3D69f4E76DB3e2B8D2B5047956": [
            {
                "pool": "0xdf55d0ebc4b62647ec83684eba9a49eb4bd4d384",
                "feeFactor": "0.9985947383062085",
                "balAndRatioFactor": "0.96",
                "wrapFactor": "1",
                "valueUSD": "16445.083753531927959541",
                "factorUSD": "15765.095142990620739778"
            }
        ],
        "0xa3E1282ac6116A698A49b2084c5c30fE1947b4A5": [
            {
                "pool": "0xdf55d0ebc4b62647ec83684eba9a49eb4bd4d384",
                "feeFactor": "0.9985947383062085",
                "balAndRatioFactor": "0.96",
                "wrapFactor": "1",
                "valueUSD": "5190.607341303488106749",
                "factorUSD": "4975.980652453671717614"
            }
        ],
        "0x42F6bB6C9138DaBD7d5290Bf6F7a9d80E4eb42b7": [
            {
                "pool": "0xf62b7d6c81274df4f2e0ee514c524c56581a3e69",
                "feeFactor": "0.9998437622063955",
                "balAndRatioFactor": "0.96",
                "wrapFactor": "1",
                "valueUSD": "0",
                "factorUSD": "0"
            }
        ],
        "0x81A5f3C04f2a7558b0f7FE7BD0C9F40a52aAfeaD": [
            {
                "pool": "0xf73f3a1e15fcec85356048c95f2d6ae54ab1a535",
                "feeFactor": "0.9961013694701175",
                "balAndRatioFactor": "1",
                "wrapFactor": "1",
                "valueUSD": "136.756623559112200828",
                "factorUSD": "136.223460011340997508"
            }
        ]
    },
    {
        "0xC4E1C8152EEb4b45b9D83C1fAa49df092dF08d51": "0.000020370552218211",
        "0xE2B52Fc1ad49B93F85C45315EcbAd740f17B0e8E": "0.120113891790039362",
        "0x048Ef78Ec97E1BcB8c1b4dc596AbAAAEAd117E28": "0",
        "0xeaB998Fa7Db98bf17788cdEAD7C7755120a55281": "0.000045093431162746",
        "0x2B86486477D007b75286474458ED45594320a580": "0.000000005127834417",
        "0x47cD5c37E276249C5DF6a94a4532E991A79788bD": "0.00000060580017091",
        "0x6A0491132aF4d0925F857A5000bb21e5C5C195EA": "3.195111710792513435",
        "0x752087ce92821c631ab223c487b9771a10C3595a": "0.00103941472082419",
        "0xb8aC6ef01a6191C8689AD756B4a41dcaD7021390": "0.0017268722332698",
        "0x2E748192b21Cbf86b80c15e75c3fdcBDf229bCdf": "0.000336508043270667",
        "0x59b8C949D5eB9feE0ba981fc3FDAa9E5B64652CE": "0.000239052120322295",
        "0x5B878ba97Bae92fc0Aa6133edbF2f58D52350d65": "0.000330174350104479",
        "0x719B8BE8E2c3f07575d41A2580011Db702029E5b": "0.000185374675534123",
        "0x95577b29A69FBa8ed9373b9F194B6515A48A82dD": "0.000017053987428474",
        "0x9b04A9EeE500302980A117F514bc2DE0Fd1f683d": "0.002546760989500696",
        "0xddf27151bcfe33DE396B472C5c5f8F48a64E3143": "0",
        "0x9e31bBA0Fa35eE9E13106baE82BccA553e774ce9": "0",
        "0xdcb48866a5Cf353aCa79467EFf1E0fFB2EC9a1eE": "0.000047043478093225",
        "0x7A0Ea4409C480fF41bC8211768fB8947c20A91eC": "0.000622745003834364",
        "0xaefcD0F8a1cbD231CecAA9bfd9Ffb82a6eaaa462": "0.001727999408275172",
        "0x1c5302aD98765D84f980a8B382EF51814A0ed2d9": "3.010524036437186912",
        "0x5B328BB20FBf15bBecC82298db269254C3FDdb5D": "0.006029416010923788",
        "0x4A4c0Ae7E2694F6F7f8A14C0A5d58967b54638ac": "0.000556859606261296",
        "0x61ea25c24067738f1f587cC9E9784A7939648559": "0.015431079558371611",
        "0xF32B6E90A3Ff5Bee0dAD681bd488cf9A023d090d": "0.03084877564946463",
        "0x52C8F15E7310D02CB7F2E20928601b86488C4397": "0",
        "0x0338CE5020c447f7e668DC2ef778025CE398266B": "0.003700927550523878",
        "0x0dC437c879FaDa4Ac7E5554b0F8F1EE78343C26B": "0.017672968585395461",
        "0x116cEb3D8d258e2A97A1f05c901Ef508809f55ec": "0.00081765690074718",
        "0x2418e5454B75e18a2C7a849aeCCFCD03f67731C3": "2.264289935688898611",
        "0xb08794f9eC5b5D19E88673fC8763243c630E828d": "0.001442020841613605",
        "0xb0a4E99371dfb0734F002ae274933b4888F618ef": "1.747878310482356128",
        "0xE380c7FE194cF2afE3477044D3c6F5D4f82343a7": "0.173423537410025138",
        "0xea7A42D29c7Ce1ed2c7F69e39152Cf1840b0A964": "0.091223756114657743",
        "0xea96EDdF997B45E22dd7cdB0EE45744f53e33693": "0.008470920659315221",
        "0x6626528DE0c75Ccc7A0d24F2D24b99060f74EdEe": "1.705145146053251417",
        "0x081aB2fa7f8F4d9E89F017ca1195b0CC75245AeE": "0.000000024859864294",
        "0x15eCd31318fa645B6496F1f21b22Ebfe3AD0c865": "0.003037329830708098",
        "0x9C7B84BE5D69BB41a718A4aF921E44730a277F90": "0.001286272543823887",
        "0xa2BfA5a2EA2E032A82E948dAD4310B069a9C8ED5": "0.00000710860367325",
        "0xCa42438C22a1BD26d48CC86aC669F23ead65e2c4": "0.000003178237656796",
        "0xED15f09337E478359C20107FC00fd6B295F9E12e": "0",
        "0xB3DA1b8a363b04D7e628C8f40E55368156949e3e": "0.00012205513760947",
        "0xC2C79Da7B83dafC2Af95F9d3CD2BE48934b9fD8B": "0.000004350680287115",
        "0x2c640AC98E293Daa246F98D2828E328A06FA6936": "0.000097997286757843",
        "0x5D6FeAE7cAFB7a6472624272971b20224B088680": "0.192886605321431568",
        "0xc36Ea7b3f0BadC0f4e3C505f84068D6bDB297eA7": "0.008863905384959851",
        "0x9f2655A391d89E27A7624328D0c0d0c9C7be924d": "0.000025108462947166",
        "0x0eE0B4D2Ff7e7b02c011178D9440D05F50cE2EE3": "0.000028543796905067",
        "0xb90829B1e57C04A77C5740638a6D8EbC32B67e92": "0.006849702693399813",
        "0xb4633912c7374cd94D8917a167449e23b46d0AD1": "0.000003567902121852",
        "0xccb78FE2dAc3349CA4415815A74e960FDae53355": "0.564864219765559417",
        "0xf4ADC8369e83D6A599e51438D44B5e53A412f807": "4.322295618492771705",
        "0x9d6EbCB3a6c96E9C52219c2cd92482F238B84826": "0",
        "0xAc7995f3cEeBe1063E64da0dEfAfb2B2051E3CD5": "0.093771802550053873",
        "0x9c754e1444fC2D7394cCEbb339670D9fEa573E4A": "0.033710364414220451",
        "0x67AFB2288621c20E4872F6FBAeb05Ab566CeD31d": "0.043412894305937816",
        "0xb5F91Aa1b639d6dA300bCcB87387007D99023302": "0.010735401363930251",
        "0x167F897440cfD5227F22349779841F83DdDA126a": "0.000070539560277297",
        "0x169833EBB85FBD3cb67eeC73Ed02f738c0017951": "0.000123550459326935",
        "0x3c9B3d0b4A42DAA68c01F34fd1DCF8615eA1fEe4": "0.000464971091694557",
        "0xA3c7a8eAF23D2dd89ed81E19a5de8C84E26B0c4E": "0.000051761212906991",
        "0xd4DC77165051bc2AeAdFf2C8A681B87163E47820": "0.00987164562594118",
        "0xe546E60D8cc8a85cF103d7B174bf1692DFA3f838": "0.000006863601351803",
        "0xEB23924B746A43Fa1143D93DfAC712b9Dc3fFfC8": "0.030669473590116639",
        "0xA7AAFFdEDf9b3A0bc0a0EFafB109a44f316C423C": "0.000001584332071807",
        "0x099C50BeE65EeCDcd209C38f1207fc334ea5eaB1": "0.002833679312948557",
        "0x78E87757861185Ec5e8C0EF6BF0C69Fa7832df6C": "0.018883027489530825",
        "0xc70c7f140d095381bFe45C9de8F16F7548547832": "0.000901374033276242",
        "0x0f820E108421D97432BeF1696205aC6F9f79EACe": "0.000033274334378255",
        "0x25a9b8B7Ff067DF3087fa015F91654360c26006C": "0.003320648979202954",
        "0x6EAA11eec98c663ba096593cc779217A7e20665a": "0.004335272455212561",
        "0x8D071fa6905E1fB872903603A6239947C03fd450": "0.000019450132483042",
        "0xbe09DE9f8caeE25C422459C1E13D6CaEd78683fD": "0.000220901492052682",
        "0xDdf900f5CaB4D248D0306A36e9bd5f78991e65B1": "0.00014327710516269",
        "0xAD4945c9ABc22e207f99e763a9F8854539a1FE5b": "0",
        "0xDeBdaF2390372E715C7F396559d1BbE1b69B53AD": "0.000121649936660137",
        "0x0a1f2e1a4585bbf5E54a894FffA74133654BfaDC": "0.007057203791146069",
        "0x12db4993126eBcd26E8dFeF76Fe3aE539b47f25b": "0.303091761565601078",
        "0x18fEe6e511646B8ea2e4964277574F637Bc03f3b": "0.066870519472035777",
        "0x1c85d6Ae1336D0e4E3F165bbfA9641bfA04CeDb1": "0.000071165903392733",
        "0x26b350F462Ae30EC1c48c36ba944AB66F06dAFee": "0.001595554883736145",
        "0x4FfD0A59a26cB2Aa76D403215e4cC2845C053994": "0.00003441661781553",
        "0x6a1afc8a229d820015361Da64819e64E6A0258F9": "0.000034311764557354",
        "0x751f556a157f8cb70d5f37086664b437F339D914": "0.000469286334926959",
        "0x7A3ba9cee390C16eC95E65C2c65961E72F8f5877": "0.003285119820776521",
        "0x7Ad5583713ca971F2aE1E0a894486a9406179eca": "0.000085865829971811",
        "0x9BDbdb4A8f7f816C87a67F5281484ED902C6b942": "0.000000824673172578",
        "0xce66C6A88bD7BEc215Aa04FDa4CF7C81055521D0": "0.111345367414349026",
        "0xd61b13A235EE8cfdef89337bb425D9323895c7Ea": "0.000022195647233706",
        "0xdec0DED0606B7d0560ADEBD6C3a919a671dB4D66": "0.131554378209534031",
        "0xe5F470E376554fB613A43FDe223e40a3bb338765": "0.000127951258355332",
        "0xF3783A4f80B2e06A6addc58D4d69B3a04aC32971": "0.001209729789518462",
        "0x09Fa38EBa245bb68354B8950FA2fe71f02863393": "0.002349352252625215",
        "0x5c41E116C162923aF27aa86Ba6dC2299f0Da313c": "0",
        "0x4E0985E556069B3D69f4E76DB3e2B8D2B5047956": "0.342418740161422223",
        "0xa3E1282ac6116A698A49b2084c5c30fE1947b4A5": "0.108078575525651776",
        "0x42F6bB6C9138DaBD7d5290Bf6F7a9d80E4eb42b7": "0",
        "0x81A5f3C04f2a7558b0f7FE7BD0C9F40a52aAfeaD": "0.002958781100553793"
    },
    {
        "0xe91D153E0b41518A2Ce8Dd3D7944Fa863463a97d": "211682.67843252694271879088221073844092816",
        "0xC45b3C1c24d5F54E7a2cF288ac668c74Dd507a84": "119270.034957341581356126265356097104091046",
        "0x63e62989D9EB2d37dfDB1F93A22f063635b07d51": "105171.85764595025780593483",
        "0xDDAfbb505ad214D7b80b1f830fcCc89B60fb7A83": "38326.635605844212173958672189153058050269",
        "0x44fA8E6f47987339850636F88629646662444217": "13.825799281263166622603645100225940421",
        "0x71850b7E9Ee3f13Ab46d67167341E4bDc905Eef9": "13883.174971878398992766597400711232350114",
        "0x3a97704a1b25F08aa230ae53B352e2e72ef52843": "82241.803000838847781969431327239665383391",
        "0x6A023CCd1ff6F2045C3309768eAd9E68F978f6e1": "175229.709748717852801824246734949980357444",
        "0xb7D311E2Eb55F2f68a9440da38e7989210b9A05e": "48995.89681621448430826992899834867057261",
        "0x8e5bBbb09Ed1ebdE8674Cda39A0c169401db4252": "70415.015005264649070410757827593927684689",
        "0x2bF2ba13735160624a0fEaE98f6aC8F70885eA61": "2092.483022013198468530181025933244478376"
    }
]